RTL/uart_tx.v
///*
//    UART TX
//    TOTAL : 10 bits
//    start bit, data bits (7) , parity bit, stop bit 
//    The data bit is converted from LSB to MSB and sent bit by bit 
//    Parity is added on the go 
//*/

module uart_tx(
    input clk,
    input rst,
    output bits
);
    reg [6:0] data_bit = 7'b1010101;     //LITTLE ENDIAN FORMAT or MSB-LSB FORMAT
    reg [3:0] i;                          //Counter Variable
    reg bit_out;
    wire pari;
    //Tx FSM
    localparam START=0, CAL_PARITY=1, TRANSMIT=2, BUFF=3;
    reg [1:0]state, next_state;

    //FF
    always@(posedge clk)begin
        if(rst) begin
            state <= 0;
        end else begin
            state <= next_state;
        end 
    end 

    //Next state logic
    always@(*)begin
        case(state)
            START: begin
                next_state = CAL_PARITY;
            end
            CAL_PARITY: begin
                next_state = TRANSMIT;
            end
            TRANSMIT: begin
                next_state = (i <= 'd7) ? BUFF : TRANSMIT;  //need to include parity too so
            end 
            BUFF: begin
                next_state = START;
            end 
        endcase 
    end 

    //Output 
    always@(posedge clk) begin
        if(rst) begin
            i<= 0;
            bit_out <= 1;
        end else begin
            case(state) 
            START: begin
                bit_out <= 1;
                i <= 0;
            end
            CAL_PARITY: begin
                //start of the start bit 
                bit_out <= 0;
                i <= 0;
                //parity 
                //I have used the comb to calculate parity
            end
            TRANSMIT: begin
                if(i < 'd7) begin
                    bit_out <= data_bit[i];  //transmit LSB -> MSB first
                end 
                else if (i == 'd7) begin
                    bit_out <= pari;
                end 
                else begin
                    bit_out <= 0;
                end 
            end 
            BUFF: begin
                i <= 0;
                bit_out <=  1;
            end 
            endcase
        end 
    end
    assign bits = bit_out;
    assign pari = ^data_bit;

endmodule

RTL/uart_rx.v
///*
//    UART :
//    Start Bit : 1
//    Data Bit  : 7
//    Parity    : 1
//    Stop Bit  : 1
//    Total     : 10
//*/

//Wrong in state logic. i might need to use the edge based method tmr @edge based method 

module uart_rx(
    input clk,
    input rst,      // Active high reset
    input bits      // Serial data in (LSB first)
);

reg [6:0] bits_reg;          // store 7-bit data
reg [2:0] i;                 // bit counter
reg parity_adder;
reg correct_frame;

localparam START_BIT  = 0,
           DATA_BITS  = 1,
           PARITY_BIT = 2,
           STOP_BIT   = 3;

reg [1:0] state, next_state;

// SEQUENTIAL: state update
always @(posedge clk) begin
    if (rst)
        state <= START_BIT;
    else
        state <= next_state;
end

// COMBINATIONAL: next state logic
always @(*) begin
    case (state)
        START_BIT  : next_state = (!bits) ? DATA_BITS : START_BIT; // wait for start bit = 0
        DATA_BITS  : next_state = (i == 6) ? PARITY_BIT : DATA_BITS;
        PARITY_BIT : next_state = STOP_BIT;
        STOP_BIT   : next_state = START_BIT;
        default    : next_state = START_BIT;
    endcase
end

// SEQUENTIAL: outputs + counters
always @(posedge clk) begin
    if (rst) begin
        bits_reg      <= 0;
        i             <= 0;
        parity_adder  <= 0;
        correct_frame <= 0;
    end else begin
        case (state)
            START_BIT: begin
                i <= 0;
                parity_adder <= 0;
                correct_frame <= 0;
            end

            DATA_BITS: begin
                bits_reg[i] <= bits;              // shift in data bit
                parity_adder <= parity_adder + bits;
                i <= i + 1;
            end

            PARITY_BIT: begin
                // simple parity check (even parity assumed)
                correct_frame <= (parity_adder == bits);
            end

            STOP_BIT: begin
                // could check stop bit == 1 here if desired
                i <= 0;
            end
        endcase
    end
end

endmodule

RTL/uart_tb.sv
`timescale 1ns/1ps

module uart_tb;

// REGISTERS
reg clk;
reg rst;
reg rx_bit;
wire tx_bit;
reg [9:0] data = 10'b1110010010; //  0101010101;
integer i;

// INITIAL RESET
initial begin
    clk = 0;
    rst = 0;
    #5 rst = 1;
    #5 rst = 0;
end 

// CLOCK GENERATION
always #5 clk = ~clk;

// TEST CASE TX to RX
initial begin 
    i = 0;
    @(negedge rst);   // wait until reset is released
    @(posedge clk);
    for (i = 0; i < 10; i = i + 1) begin
        rx_bit = data[i];   // drive next bit
        @(posedge clk);     // wait 1 cycle
    end
    #20;   // wait a little more
    $finish; // stop simulation
end 

// TEST CASE TX to DISPLAY
always @(posedge clk) begin
    $display("Time=%0t TX Data=%b", $time, tx_bit);
end 

// MODULE INSTANTIATION
uart_rx rx (
    .clk(clk),
    .rst(rst),
    .bits(rx_bit)
);

uart_tx tx (
    .clk(clk),
    .rst(rst),
    .bits(tx_bit)
);
//FOR GTKWAVE
initial begin
    $dumpfile("build/uart.vcd");   // create VCD file
    $dumpvars(0, uart_tb);   // dump all signals in uart_tb
end

endmodule

build/uart.vcd
$date
	Tue Aug 19 16:39:25 2025
$end
$version
	Icarus Verilog
$end
$timescale
	1ps
$end
$scope module uart_tb $end
$var wire 1 ! tx_bit $end
$var reg 1 " clk $end
$var reg 10 # data [9:0] $end
$var reg 1 $ rst $end
$var reg 1 % rx_bit $end
$var integer 32 & i [31:0] $end
$scope module rx $end
$var wire 1 % bits $end
$var wire 1 " clk $end
$var wire 1 $ rst $end
$var reg 7 ' bits_reg [6:0] $end
$var reg 1 ( correct_frame $end
$var reg 3 ) i [2:0] $end
$var reg 2 * next_state [1:0] $end
$var reg 1 + parity_adder $end
$var reg 2 , state [1:0] $end
$upscope $end
$scope module tx $end
$var wire 1 ! bits $end
$var wire 1 " clk $end
$var wire 1 $ rst $end
$var wire 1 - pari $end
$var reg 1 . bit_out $end
$var reg 7 / data_bit [6:0] $end
$var reg 4 0 i [3:0] $end
$var reg 2 1 next_state [1:0] $end
$var reg 2 2 state [1:0] $end
$upscope $end
$upscope $end
$enddefinitions $end
#0
$dumpvars
bx 2
bx 1
bx 0
b1010101 /
x.
0-
bx ,
x+
bx *
bx )
x(
bx '
b0 &
x%
0$
b1110010010 #
0"
x!
$end
#5000
b0x *
b1 1
b0 ,
0(
0+
b0 )
b0 '
b0 2
1!
1.
b0 0
1"
1$
#10000
0"
0$
#15000
b10 1
b1 2
b0x ,
b0 *
0%
1"
#20000
0"
#25000
b11 1
b0 ,
b10 2
0!
0.
1%
b1 &
1"
#30000
0"
#35000
b0 1
1!
1.
b11 2
b1 *
0%
b10 &
1"
#40000
0"
#45000
b1 1
b1 ,
b0 2
b11 &
1"
#50000
0"
#55000
b10 1
b1 2
b1 )
1+
b1 '
1%
b100 &
1"
#60000
0"
#65000
b11 1
b10 )
0+
b11 '
b10 2
0!
0.
0%
b101 &
1"
#70000
0"
#75000
b0 1
1!
1.
b11 2
b11 )
b110 &
1"
#80000
0"
#85000
b1 1
b100 )
b0 2
1%
b111 &
1"
#90000
0"
#95000
b10 1
b1 2
b101 )
1+
b10011 '
b1000 &
1"
#100000
0"
#105000
b10 *
b11 1
b110 )
0+
b110011 '
b10 2
0!
0.
b1001 &
1"
#110000
0"
#115000
b0 1
b11 *
1!
1.
b11 2
b111 )
1+
b1110011 '
b10 ,
b1010 &
1"
#120000
0"
#125000
b0 *
b1 1
b11 ,
1(
b0 2
1"
#130000
0"
#135000
b10 1
b1 2
b0 )
b0 ,
1"
